Metadata-Version: 1.0
Name: distrib-bin-gauss
Version: 0.1
Summary: Gaussian and Binomial distributions
Home-page: UNKNOWN
Author: UNKNOWN
Author-email: abitbol.ouriel@gmail.com
License: UNKNOWN
Platform: UNKNOWN
